README.md
setup.py
wok/__init__.py
wok/cli.py
wok/debug.py
wok/parser.py
wok/formatters/__init__.py
wok/formatters/formatter.py
wok/formatters/html.py
wok/formatters/txt.py
wok/nodes/__init__.py
wok/nodes/heading_node.py
wok/nodes/meta_node.py
wok/nodes/node.py
wok/nodes/root_node.py
wok/nodes/table_node.py
wok_compiler.egg-info/PKG-INFO
wok_compiler.egg-info/SOURCES.txt
wok_compiler.egg-info/dependency_links.txt
wok_compiler.egg-info/entry_points.txt
wok_compiler.egg-info/requires.txt
wok_compiler.egg-info/top_level.txt