Metadata-Version: 2.1
Name: wok-compiler
Version: 0.1.0
Summary: Advanced yet human-readable markup language
Home-page: https://gitlab.com/tijlvdb/wok
Author: Tijl Van den Brugghen
Author-email: me@tijlvdb.me
License: MIT
Platform: UNKNOWN
Classifier: License :: OSI Approved :: MIT License
Classifier: Development Status :: 1 - Planning
Classifier: Programming Language :: Python :: 3
